icw/__init__.py
icw/api.py
icw/cli.py
icw/static/explorer.html
icw/static/index.html
icw/static/logo.png
internet_computer_wallet-0.3.3.dist-info/licenses/LICENSE
internet_computer_wallet-0.3.3.dist-info/METADATA
internet_computer_wallet-0.3.3.dist-info/WHEEL
internet_computer_wallet-0.3.3.dist-info/entry_points.txt
internet_computer_wallet-0.3.3.dist-info/top_level.txt
internet_computer_wallet-0.3.3.dist-info/RECORD
