Metadata-Version: 2.4
Name: internet-computer-wallet
Version: 0.3.3
Summary: CLI for ICRC-1 tokens (ckBTC, ckETH, ICP, ckUSDC, ckUSDT) on the Internet Computer
License: MIT
Project-URL: Repository, https://github.com/smart-social-contracts/icw
Keywords: icp,ckbtc,icrc-1,dfx,wallet
Classifier: Programming Language :: Python :: 3
Classifier: License :: OSI Approved :: MIT License
Requires-Python: >=3.9
License-File: LICENSE
Provides-Extra: dev
Requires-Dist: ruff>=0.4; extra == "dev"
Requires-Dist: black>=24.0; extra == "dev"
Provides-Extra: ui
Requires-Dist: fastapi>=0.109.0; extra == "ui"
Requires-Dist: uvicorn>=0.27.0; extra == "ui"
Provides-Extra: test
Requires-Dist: httpx>=0.26.0; extra == "test"
Requires-Dist: playwright>=1.40.0; extra == "test"
Dynamic: license-file
